splent_io/splent_feature_auth/__init__.py
splent_io/splent_feature_auth/decorators.py
splent_io/splent_feature_auth/forms.py
splent_io/splent_feature_auth/hooks.py
splent_io/splent_feature_auth/models.py
splent_io/splent_feature_auth/repositories.py
splent_io/splent_feature_auth/routes.py
splent_io/splent_feature_auth/seeders.py
splent_io/splent_feature_auth/services.py
splent_io/splent_feature_auth/tests/__init__.py
splent_io/splent_feature_auth/tests/conftest.py
splent_io/splent_feature_auth/tests/locustfile.py
splent_io/splent_feature_auth/tests/test_selenium.py
splent_io/splent_feature_auth/tests/functional/test_login_flow.py
splent_io/splent_feature_auth/tests/integration/test_login_integration.py
splent_io/splent_feature_auth/tests/test_selenium_ide/test_signup.py
splent_io/splent_feature_auth/tests/unit/test_auth_service.py
splent_feature_auth-1.0.4.dist-info/METADATA
splent_feature_auth-1.0.4.dist-info/WHEEL
splent_feature_auth-1.0.4.dist-info/top_level.txt
splent_feature_auth-1.0.4.dist-info/RECORD
