Metadata-Version: 2.4
Name: splent_feature_auth
Version: 1.0.4
Author-email: DiversoLab <diversolab@us.es>
Requires-Python: >=3.12
Requires-Dist: email_validator
